joecomp/__init__.py
joecomp/chemistry_properties.py
joecomp/colour_maps.py
joecomp/disc_loader.py
joecomp/import_config.py
joecomp/planet_loader.py
joecomp-1.4.9.dist-info/LICENSE.txt
joecomp-1.4.9.dist-info/METADATA
joecomp-1.4.9.dist-info/WHEEL
joecomp-1.4.9.dist-info/top_level.txt
joecomp-1.4.9.dist-info/RECORD
